khawla_package/__init__.py
khawla_package/khawla_module.py
khawla_package-1.0.0.dist-info/LICENSE.txt
khawla_package-1.0.0.dist-info/METADATA
khawla_package-1.0.0.dist-info/WHEEL
khawla_package-1.0.0.dist-info/top_level.txt
khawla_package-1.0.0.dist-info/RECORD
