Metadata-Version: 2.1
Name: khawla-package
Version: 1.0.0
Summary: An awesome package that does something
Home-page: http://pypi.python.org/pypi/khawla_package/
Author: khawla senkadi
Author-email: k.senkadi@esi-sba.dz
License: LICENSE.txt
License-File: LICENSE.txt
Requires-Dist: khawla-package
